gemtip/__init__.py
gemtip/emt.py
gemtip/integrals.py
gemtip/network.py
gemtip/plotlib.py
gemtip/utilities.py
gemtip_ml-0.1.dist-info/LICENSE
gemtip_ml-0.1.dist-info/METADATA
gemtip_ml-0.1.dist-info/WHEEL
gemtip_ml-0.1.dist-info/top_level.txt
gemtip_ml-0.1.dist-info/RECORD
